cloe_util_git_client/__init__.py
cloe_util_git_client/git_client.py
cloe_util_git_client/py.typed
cloe_util_git_client-2.0.2.dist-info/METADATA
cloe_util_git_client-2.0.2.dist-info/WHEEL
cloe_util_git_client-2.0.2.dist-info/RECORD
