Metadata-Version: 2.4
Name: cloe-util-git-client
Version: 2.0.2
Summary: This package contains a git client which can be used to retrieve files from git history and interact with it.
Author-email: initions <ICSMC_EXT_PYPIORG@accenture.com>
License: MIT
Classifier: Development Status :: 5 - Production/Stable
Classifier: Environment :: Console
Classifier: Intended Audience :: Developers
Classifier: License :: OSI Approved :: MIT License
Classifier: Operating System :: OS Independent
Classifier: Programming Language :: Python :: 3
Classifier: Topic :: Database
Requires-Python: <3.12,>=3.11
Requires-Dist: gitpython~=3.1.41
Requires-Dist: pyyaml~=6.0.1
